nbsv/__init__.py
nbsv/_frontend.py
nbsv/_version.py
nbsv/viewer.py
nbsv/labextension/package.json
nbsv/labextension/static/122.d01b6c66ff7ba9de7020.js
nbsv/labextension/static/159.475537c6067d0b5ce836.js
nbsv/labextension/static/247.106d96439364781cd7da.js
nbsv/labextension/static/247.106d96439364781cd7da.js.LICENSE.txt
nbsv/labextension/static/417.53db114a0378aeb0b2db.js
nbsv/labextension/static/485.6426a26ad4f61ac6a66f.js
nbsv/labextension/static/485.6426a26ad4f61ac6a66f.js.LICENSE.txt
nbsv/labextension/static/488.dbd2c3e142c7db279ca7.js
nbsv/labextension/static/488.dbd2c3e142c7db279ca7.js.LICENSE.txt
nbsv/labextension/static/490.05f401b8ffcb2c8e27af.js
nbsv/labextension/static/490.05f401b8ffcb2c8e27af.js.LICENSE.txt
nbsv/labextension/static/509.5e27dcbcd60d84f1d64e.js
nbsv/labextension/static/866.52aaca5d462d43c0b80b.js
nbsv/labextension/static/866.52aaca5d462d43c0b80b.js.LICENSE.txt
nbsv/labextension/static/885.3a7df8d0d1fec24f5c6e.js
nbsv/labextension/static/885.3a7df8d0d1fec24f5c6e.js.LICENSE.txt
nbsv/labextension/static/952.6c013ac49d113d5a8f80.js
nbsv/labextension/static/975.f44df50745024af9692a.js
nbsv/labextension/static/975.f44df50745024af9692a.js.LICENSE.txt
nbsv/labextension/static/remoteEntry.355ea2ec304267e4a5e8.js
nbsv/labextension/static/style.js
nbsv/labextension/static/third-party-licenses.json
nbsv/nbextension/extension.js
nbsv/nbextension/index.js
nbsv/nbextension/index.js.map
nbsv/tests/__init__.py
nbsv/tests/conftest.py
nbsv/tests/test_example.py
nbsv/tests/test_nbextension_path.py
nbsv-0.1.6.data/data/share/jupyter/labextensions/nbsv/package.json
nbsv-0.1.6.data/data/share/jupyter/labextensions/nbsv/static/122.d01b6c66ff7ba9de7020.js
nbsv-0.1.6.data/data/share/jupyter/labextensions/nbsv/static/159.475537c6067d0b5ce836.js
nbsv-0.1.6.data/data/share/jupyter/labextensions/nbsv/static/247.106d96439364781cd7da.js
nbsv-0.1.6.data/data/share/jupyter/labextensions/nbsv/static/247.106d96439364781cd7da.js.LICENSE.txt
nbsv-0.1.6.dist-info/METADATA
nbsv-0.1.6.dist-info/WHEEL
nbsv-0.1.6.dist-info/licenses/LICENSE.txt
nbsv-0.1.6.dist-info/RECORD
