Metadata-Version: 2.3
Name: nbsv
Version: 0.1.6
Summary: Simularium Viewer Jupyter Widget 
Project-URL: Homepage, https://github.com/simularium/nbsv
Author-email: Megan Riel-Mehan <meganr@alleninstitute.org>
License: Copyright (c) 2023 Megan Riel-Mehan
License-File: LICENSE.txt
Keywords: IPython,Jupyter,Widgets
Classifier: Framework :: Jupyter
Classifier: Intended Audience :: Developers
Classifier: Intended Audience :: Science/Research
Classifier: License :: OSI Approved :: BSD License
Classifier: Programming Language :: Python
Classifier: Programming Language :: Python :: 3
Classifier: Programming Language :: Python :: 3.7
Classifier: Programming Language :: Python :: 3.8
Classifier: Programming Language :: Python :: 3.9
Classifier: Programming Language :: Python :: 3.10
Requires-Python: >=3.7
Requires-Dist: ipydatawidgets>=4.3.2
Requires-Dist: ipywidgets==8.0.4
Requires-Dist: jupyter-packaging>=0.12.3
Requires-Dist: jupyter>=1.0.0
Requires-Dist: jupyterlab==3.5.2
Requires-Dist: numpy>=1.14.3
Requires-Dist: simulariumio
Provides-Extra: docs
Requires-Dist: jupyter-sphinx; extra == 'docs'
Requires-Dist: nbsphinx; extra == 'docs'
Requires-Dist: nbsphinx-link; extra == 'docs'
Requires-Dist: pypandoc; extra == 'docs'
Requires-Dist: pytest-check-links; extra == 'docs'
Requires-Dist: recommonmark; extra == 'docs'
Requires-Dist: sphinx-rtd-theme; extra == 'docs'
Requires-Dist: sphinx>=1.5; extra == 'docs'
Provides-Extra: examples
Requires-Dist: numpy; extra == 'examples'
Requires-Dist: simulariumio; extra == 'examples'
Provides-Extra: test
Requires-Dist: nbval; extra == 'test'
Requires-Dist: pytest-cov; extra == 'test'
Requires-Dist: pytest>=7.1; extra == 'test'
Requires-Dist: tbump; extra == 'test'
